canny_chenn/__init__.py
canny_chenn/canny.py
canny_chenn/py.typed
canny_chenn-1.0.5.dist-info/WHEEL
canny_chenn-1.0.5.dist-info/METADATA
canny_chenn-1.0.5.dist-info/RECORD
