Metadata-Version: 2.4
Name: canny-chenn
Version: 1.0.5
Summary: A simple Canny edge detector for pytorch
Keywords: computer vision,edge detection,opencv
Author: Christian Henn
Author-email: Christian Henn <chenn@alum.mit.edu>
License-Expression: MIT
Classifier: Development Status :: 4 - Beta
Classifier: Programming Language :: Python
Classifier: Programming Language :: Python :: 3.13
Requires-Dist: numpy>=2.3.5
Requires-Dist: torch>=2.9.1
Requires-Python: >=3.12, <3.14
Project-URL: Repository, https://github.com/chrishenn/canny
